aui/__init__.py
aui/apollo_ws_session/__init__.py
aui/apollo_ws_session/client.py
aui/apollo_ws_session/raw_client.py
aui/apollo_ws_session/socket_client.py
aui/client.py
aui/controller_api/__init__.py
aui/controller_api/client.py
aui/controller_api/raw_client.py
aui/core/__init__.py
aui/core/api_error.py
aui/core/client_wrapper.py
aui/core/datetime_utils.py
aui/core/events.py
aui/core/file.py
aui/core/force_multipart.py
aui/core/http_client.py
aui/core/http_response.py
aui/core/http_sse/__init__.py
aui/core/http_sse/_api.py
aui/core/http_sse/_decoders.py
aui/core/http_sse/_exceptions.py
aui/core/http_sse/_models.py
aui/core/jsonable_encoder.py
aui/core/pydantic_utilities.py
aui/core/query_encoder.py
aui/core/remove_none_from_dict.py
aui/core/request_options.py
aui/core/serialization.py
aui/environment.py
aui/errors/__init__.py
aui/errors/unprocessable_entity_error.py
aui/py.typed
aui/types/__init__.py
aui/types/actor.py
aui/types/card.py
aui/types/card_parameter.py
aui/types/context.py
aui/types/create_task_response.py
aui/types/error_message_payload.py
aui/types/final_message_payload.py
aui/types/http_validation_error.py
aui/types/list_tasks_response.py
aui/types/message.py
aui/types/message_contact_party.py
aui/types/parameter_type.py
aui/types/product_card.py
aui/types/product_parameter.py
aui/types/product_parameter_type.py
aui/types/product_parameter_value.py
aui/types/streaming_update_payload.py
aui/types/streaming_update_payload_channel.py
aui/types/streaming_update_payload_data.py
aui/types/streaming_update_payload_scope.py
aui/types/streaming_update_payload_scope_context.py
aui/types/streaming_update_payload_scope_data.py
aui/types/streaming_update_payload_scope_data_status.py
aui/types/user_message_payload.py
aui/types/validation_error.py
aui/types/validation_error_loc_item.py
aui/types/ws_actor.py
aui/types/ws_actor_type.py
aui/version.py
aui_client-1.2.13.dist-info/METADATA
aui_client-1.2.13.dist-info/WHEEL
aui_client-1.2.13.dist-info/RECORD
